ai_common_utilss/__init__.py
ai_common_utilss/cli/__init__.py
ai_common_utilss/cli/main.py
ai_common_utilss/trainer/__init__.py
ai_common_utilss/trainer/trainer.py
ai_common_utilss-0.1.3.dist-info/entry_points.txt
ai_common_utilss-0.1.3.dist-info/METADATA
ai_common_utilss-0.1.3.dist-info/WHEEL
ai_common_utilss-0.1.3.dist-info/RECORD
