Metadata-Version: 2.3
Name: ai-common-utilss
Version: 0.1.3
Summary: 
Author: venkatkedar007
Author-email: abc@gmail.com
Requires-Python: >=3.12
Classifier: Programming Language :: Python :: 3
Classifier: Programming Language :: Python :: 3.12
Classifier: Programming Language :: Python :: 3.13
Requires-Dist: ai-text-utils
Requires-Dist: numpy
Requires-Dist: torch
